binance_c2c/__init__.py
binance_c2c/api.py
cs_binance_c2c_sapi-0.0.11.dist-info/METADATA
cs_binance_c2c_sapi-0.0.11.dist-info/WHEEL
cs_binance_c2c_sapi-0.0.11.dist-info/top_level.txt
cs_binance_c2c_sapi-0.0.11.dist-info/RECORD
